nrt/validate/__init__.py
nrt/validate/algorithm_selection.py
nrt/validate/composites.py
nrt/validate/estimators.py
nrt/validate/fitting.py
nrt/validate/indices.py
nrt/validate/interface.py
nrt/validate/loaders.py
nrt/validate/metrics.py
nrt/validate/sampling.py
nrt/validate/segments.py
nrt/validate/utils.py
nrt/validate/webmaps.py
nrt/validate/xr_transforms.py
nrt/validate/notebooks/demo_notebook.ipynb
nrt/validate/nrtval/__init__.py
nrt/validate/static/ec-logo.png
nrt_validate-0.0.1a6.dist-info/LICENSE
nrt_validate-0.0.1a6.dist-info/METADATA
nrt_validate-0.0.1a6.dist-info/WHEEL
nrt_validate-0.0.1a6.dist-info/entry_points.txt
nrt_validate-0.0.1a6.dist-info/top_level.txt
nrt_validate-0.0.1a6.dist-info/RECORD
