Metadata-Version: 2.2
Name: nrt-validate
Version: 0.0.1a6
Summary: Validation of alerting system results produced by tools like nrt
Author: Keith Arano, Jonas Viehweger
Author-email: Loic Dutrieux <loic.dutrieux@ec.europa.eu>
License: EUPL-1.2
Project-URL: homepage, https://code.europa.eu/jrc-forest/nrt-validate
Keywords: sentinel2,xarray,validation,forest,monitoring,change
Classifier: Programming Language :: Python :: 3
Classifier: Programming Language :: Python :: 3.9
Classifier: Programming Language :: Python :: 3.10
Classifier: Programming Language :: Python :: 3.11
Classifier: License :: OSI Approved :: European Union Public Licence 1.2 (EUPL 1.2)
Requires-Python: >=3.9
License-File: LICENSE
Requires-Dist: numpy
Requires-Dist: xarray
Requires-Dist: pandas
Requires-Dist: IPython
Requires-Dist: ipywidgets
Requires-Dist: ipyevents
Requires-Dist: ipyleaflet
Requires-Dist: bqplot
Requires-Dist: traitlets
Requires-Dist: rasterio
Requires-Dist: rioxarray
Requires-Dist: pyproj
Requires-Dist: affine
Requires-Dist: shapely
Requires-Dist: rtree
Requires-Dist: Pillow
Requires-Dist: netCDF4
Requires-Dist: kneed
Requires-Dist: requests
Requires-Dist: click
Requires-Dist: nrt-data
Requires-Dist: voila
Requires-Dist: ipykernel
Provides-Extra: dask
Requires-Dist: dask; extra == "dask"
Provides-Extra: stac
Requires-Dist: pystac-client; extra == "stac"
Requires-Dist: odc-stac; extra == "stac"
Provides-Extra: docs
Requires-Dist: sphinx; extra == "docs"
Requires-Dist: sphinx_rtd_theme; extra == "docs"
